aap_dspy/__init__.py
aap_dspy/chain.py
aap_dspy/py.typed
aap_dspy-0.1.2.dev1.dist-info/WHEEL
aap_dspy-0.1.2.dev1.dist-info/METADATA
aap_dspy-0.1.2.dev1.dist-info/RECORD
