Metadata-Version: 2.3
Name: aap-dspy
Version: 0.1.2.dev1
Summary: DsPy integration of agent design pattern
Author: Ly Hon Quang
Author-email: Ly Hon Quang <lyhonquang@gmail.com>
License: MIT
Requires-Dist: aap-core>=0.1.0
Requires-Dist: dspy>=3.0.4
Requires-Python: >=3.10.12
